pynorare/__init__.py
pynorare/__main__.py
pynorare/api.py
pynorare/cli_util.py
pynorare/files.py
pynorare/util.py
pynorare/commands/__init__.py
pynorare/commands/check.py
pynorare/commands/download.py
pynorare/commands/ls.py
pynorare/commands/map.py
pynorare/commands/stats.py
pynorare/commands/validate.py
pynorare-1.1.0.dist-info/LICENSE
pynorare-1.1.0.dist-info/METADATA
pynorare-1.1.0.dist-info/WHEEL
pynorare-1.1.0.dist-info/entry_points.txt
pynorare-1.1.0.dist-info/top_level.txt
pynorare-1.1.0.dist-info/RECORD
